[
  {
    "payload_length_bytes": 14,
    "rx_samples": 262144,
    "sync_preamble_symbols": 372,
    "channel_payload_symbols": 12374,
    "midamble_symbols": 62,
    "midamble_applied": true,
    "sync_input_samples": 262144,
    "sync_input_offset": 0,
    "burst_crop_window_samples": 102976,
    "burst_crop_margin_samples": 80,
    "burst_crop_full_buffer_fallback": false,
    "header_alignment_detected": true,
    "header_alignment_applied": true,
    "header_alignment_soft_selected": false,
    "header_alignment_peak": 0.9987024664878845,
    "header_alignment_phase_score": 0.9999252557754517,
    "header_alignment_peak_ratio": 1.0415953146805197,
    "header_alignment_start_sample": 63307,
    "header_alignment_offset_samples": 63291,
    "header_phase": 4,
    "header_phase_score": 0.9999252557754517,
    "header_phase_offset_samples": -4,
    "refined_header_start_sample": 12,
    "matched_rms_before": 389.9190673828125,
    "matched_normalization_scale": 0.0025646347759090884,
    "matched_normalization_selected_samples": 91751,
    "fractional_timing_enabled": true,
    "fractional_timing_applied": true,
    "fractional_timing_reason": "applied",
    "fractional_timing_sample_offset": -1.0,
    "fractional_timing_baseline_header_peak": 0.6129032373428345,
    "fractional_timing_baseline_header_error": 0.5447306688033394,
    "fractional_timing_header_peak": 1.0,
    "fractional_timing_header_error": 0.3929609674397573,
    "fractional_timing_best_index": 374,
    "timing_header_index": 372,
    "timing_header_peak": 1.0,
    "timing_header_rotation": "(1+0j)",
    "timing_header_detect_ok": true,
    "timing_header_best_index": 372,
    "timing_header_best_index_error": 0,
    "timing_header_slip_symbols": 0,
    "timing_header_slip_applied": false,
    "timing_header_error": 0.3929609674397573,
    "timing_header_index_error": 0,
    "header_phase_symbol_index": 372,
    "timing_window_start_sample": 4,
    "timing_window_stop_sample": 102820,
    "timing_window_samples": 102816,
    "timing_window_requested_symbols": 12850,
    "timing_window_available_symbols": 12852,
    "timing_window_expected_preamble_index": 0,
    "timing_window_active_symbols": 12808,
    "timing_window_tracking_payload_symbols": 64,
    "timing_window_tracking_symbols": 498,
    "timing_window_post_symbols": 412,
    "gardner_update_start_sample": 0,
    "gardner_update_stop_sample": 3984,
    "gardner_gate_min_energy": 1.0935558378696442,
    "gardner_gate_max_energy": 4.801967024803162,
    "gardner_update_rate": 0.03867403417825699,
    "gardner_mu_final": 0.05005645751953125,
    "gardner_omega_final": 8.000003814697266,
    "preamble_cfo_enabled": true,
    "preamble_cfo_repeat_count": 12,
    "preamble_cfo_repeat_length_symbols": 31,
    "preamble_cfo_symbol_index": 0,
    "preamble_cfo_score": 0.9888089043912327,
    "preamble_cfo_reason": "applied",
    "preamble_cfo_phase_slope_rad_per_symbol": -6.38118060384011e-07,
    "preamble_cfo_applied_slope_rad_per_symbol": -6.38118060384011e-07,
    "preamble_cfo_frequency_hz": -0.012694955448290988,
    "preamble_cfo_applied_frequency_hz": -0.012694955448290988,
    "preamble_symbol_best_index": 2,
    "preamble_symbol_score": 0.9069997619039142,
    "preamble_symbol_peak_ratio": 1.0115724004638298,
    "preamble_symbol_slip_symbols": 2,
    "preamble_symbol_alignment_applied": true,
    "preamble_symbol_alignment_reason": "applied",
    "header_carrier_phase_rad": -1.1501622438636074,
    "header_carrier_phase_slope_rad_per_symbol": -7.357157066669864e-06,
    "header_carrier_frequency_hz": -0.1463659892829972,
    "header_carrier_score": 0.8930559875938636,
    "header_carrier_applied_slope_rad_per_symbol": -7.357157066669864e-06,
    "header_carrier_applied_frequency_hz": -0.1463659892829972,
    "header_carrier_slope_applied": true,
    "header_carrier_slope_reason": "applied",
    "header_carrier_branch_selection_enabled": true,
    "header_carrier_selected_branch": "phase_slope",
    "header_carrier_selection_reason": "best_header_error",
    "header_carrier_selected_detect_peak": 1.0,
    "header_carrier_selected_header_score": 0.8930559533167848,
    "header_carrier_selected_header_error": 0.39296060813372646,
    "header_carrier_phase_only_peak": 1.0,
    "header_carrier_phase_only_score": 0.8930558931476504,
    "header_carrier_phase_only_error": 0.3929609677592366,
    "header_carrier_phase_slope_peak": 1.0,
    "header_carrier_phase_slope_score": 0.8930559533167848,
    "header_carrier_phase_slope_error": 0.39296060813372646,
    "short_equalizer_enabled": true,
    "short_equalizer_applied": true,
    "short_equalizer_reason": "header_error_improved_peak_within_tol",
    "short_equalizer_tap_count": 5,
    "short_equalizer_training_symbols": 434,
    "short_equalizer_valid_training_symbols": 434,
    "short_equalizer_before_error": 0.5744695936595572,
    "short_equalizer_after_error": 0.4533545838056203,
    "short_equalizer_before_mse": 0.35143506508989053,
    "short_equalizer_after_mse": 0.2199087707556165,
    "short_equalizer_mse_relative_improvement": 0.3742548977024591,
    "short_equalizer_mse_relative_improvement_min": 0.05,
    "short_equalizer_peak_tolerance": 0.001,
    "short_equalizer_baseline_header_peak": 1.0,
    "short_equalizer_baseline_header_error": 0.39296060813372646,
    "short_equalizer_post_header_peak": 1.0,
    "short_equalizer_post_header_error": 0.2377569502802303,
    "short_equalizer_post_header_score": 0.9670402643818736,
    "short_equalizer_header_peak_improved": false,
    "short_equalizer_header_peak_within_tol": true,
    "short_equalizer_header_error_improved": true,
    "short_equalizer_header_error_not_worse": true,
    "short_equalizer_accepted_via_header_error": true,
    "short_equalizer_accepted_via_training_mse": true,
    "short_equalizer_header_gate_passed": true,
    "short_equalizer_acceptance_reason": "header_error_improved_peak_within_tol",
    "short_equalizer_rejection_reason": "",
    "short_equalizer_post_header_best_index": 372,
    "midamble_alignment_enabled": true,
    "midamble_alignment_applied": false,
    "midamble_alignment_reason": "not_improved",
    "midamble_expected_index": 1458,
    "midamble_best_index": 1458,
    "midamble_slip_symbols": 0,
    "midamble_score": 0.9807909900032526,
    "midamble_peak": 1.0,
    "midamble_phase_rad": 0.0,
    "midamble_error": 0.12170933806346479,
    "costas_update_start_symbol": 372,
    "costas_update_stop_symbol": 12808,
    "costas_gate_reference_power": 0.40434515476226807,
    "costas_gate_min_power": 0.19693952798843384,
    "costas_gate_max_power": 0.6940288543701172,
    "costas_update_rate": 0.6773014068603516,
    "timing_nearest_symbol_error": 1.0827505588531494,
    "carrier_aligned_nearest_symbol_error": 0.4558470845222473,
    "equalized_nearest_symbol_error": 0.3692876994609833,
    "fine_nearest_symbol_error": 0.36774125695228577,
    "tx_symbols": 12872,
    "payload_symbols": 12312,
    "gold_header_symbols": 62,
    "guard_symbols": 32,
    "detected": true,
    "detected_index": 372,
    "decode_candidate_count": 1,
    "decode_candidate_min_peak": 0.65,
    "decode_candidates_ranked": 5,
    "decode_candidates_attempted": 1,
    "expected_header_index": 372,
    "timing_window_expected_header_index": 372,
    "header_detect_ok": true,
    "peak": 1.0,
    "best_symbol_phase": 0,
    "detection_rotation": "(1+0j)",
    "recovered_ok": true,
    "decode_rotation": "(1+0j)",
    "decode_error": "",
    "recovered_text": "hardware test ",
    "costas_error_mean": 0.043066877871751785,
    "costas_error_variance": 0.0024675284512341022,
    "costas_phase_span": 0.004451507702469826,
    "gardner_error_mean": 0.0028138409834355116,
    "gardner_error_variance": 0.013799387961626053,
    "run_index": 1
  },
  {
    "payload_length_bytes": 14,
    "rx_samples": 262144,
    "sync_preamble_symbols": 372,
    "channel_payload_symbols": 12374,
    "midamble_symbols": 62,
    "midamble_applied": true,
    "sync_input_samples": 262144,
    "sync_input_offset": 0,
    "burst_crop_window_samples": 102976,
    "burst_crop_margin_samples": 80,
    "burst_crop_full_buffer_fallback": false,
    "header_alignment_detected": true,
    "header_alignment_applied": true,
    "header_alignment_soft_selected": false,
    "header_alignment_peak": 0.9853363633155823,
    "header_alignment_phase_score": 0.9863657355308533,
    "header_alignment_peak_ratio": 1.0395134173007992,
    "header_alignment_start_sample": 136818,
    "header_alignment_offset_samples": 136802,
    "header_phase": 4,
    "header_phase_score": 0.9863657355308533,
    "header_phase_offset_samples": -4,
    "refined_header_start_sample": 12,
    "matched_rms_before": 384.8634948730469,
    "matched_normalization_scale": 0.0025983238559164085,
    "matched_normalization_selected_samples": 91751,
    "fractional_timing_enabled": true,
    "fractional_timing_applied": true,
    "fractional_timing_reason": "applied",
    "fractional_timing_sample_offset": -1.0,
    "fractional_timing_baseline_header_peak": 0.6129032373428345,
    "fractional_timing_baseline_header_error": 0.5449367013531573,
    "fractional_timing_header_peak": 1.0,
    "fractional_timing_header_error": 0.3931368332622361,
    "fractional_timing_best_index": 374,
    "timing_header_index": 372,
    "timing_header_peak": 1.0,
    "timing_header_rotation": "(1+0j)",
    "timing_header_detect_ok": true,
    "timing_header_best_index": 372,
    "timing_header_best_index_error": 0,
    "timing_header_slip_symbols": 0,
    "timing_header_slip_applied": false,
    "timing_header_error": 0.3931368332622361,
    "timing_header_index_error": 0,
    "header_phase_symbol_index": 372,
    "timing_window_start_sample": 4,
    "timing_window_stop_sample": 102820,
    "timing_window_samples": 102816,
    "timing_window_requested_symbols": 12850,
    "timing_window_available_symbols": 12852,
    "timing_window_expected_preamble_index": 0,
    "timing_window_active_symbols": 12808,
    "timing_window_tracking_payload_symbols": 64,
    "timing_window_tracking_symbols": 498,
    "timing_window_post_symbols": 412,
    "gardner_update_start_sample": 0,
    "gardner_update_stop_sample": 3984,
    "gardner_gate_min_energy": 1.1045222282409668,
    "gardner_gate_max_energy": 4.872313499450684,
    "gardner_update_rate": 0.03867403417825699,
    "gardner_mu_final": 0.050197601318359375,
    "gardner_omega_final": 8.000003814697266,
    "preamble_cfo_enabled": true,
    "preamble_cfo_repeat_count": 12,
    "preamble_cfo_repeat_length_symbols": 31,
    "preamble_cfo_symbol_index": 0,
    "preamble_cfo_score": 0.9888679701526449,
    "preamble_cfo_reason": "applied",
    "preamble_cfo_phase_slope_rad_per_symbol": 0.0015311474034702247,
    "preamble_cfo_applied_slope_rad_per_symbol": 0.0015311474034702247,
    "preamble_cfo_frequency_hz": 30.46120973307587,
    "preamble_cfo_applied_frequency_hz": 30.46120973307587,
    "preamble_symbol_best_index": 2,
    "preamble_symbol_score": 0.907102177055073,
    "preamble_symbol_peak_ratio": 1.0119499923588067,
    "preamble_symbol_slip_symbols": 2,
    "preamble_symbol_alignment_applied": true,
    "preamble_symbol_alignment_reason": "applied",
    "header_carrier_phase_rad": -0.08561257249419338,
    "header_carrier_phase_slope_rad_per_symbol": 1.813415832674287e-05,
    "header_carrier_frequency_hz": 0.3607676170640227,
    "header_carrier_score": 0.892725783028938,
    "header_carrier_applied_slope_rad_per_symbol": 1.813415832674287e-05,
    "header_carrier_applied_frequency_hz": 0.3607676170640227,
    "header_carrier_slope_applied": true,
    "header_carrier_slope_reason": "applied",
    "header_carrier_branch_selection_enabled": true,
    "header_carrier_selected_branch": "phase_slope",
    "header_carrier_selection_reason": "best_header_error",
    "header_carrier_selected_detect_peak": 1.0,
    "header_carrier_selected_header_score": 0.892725703686306,
    "header_carrier_selected_header_error": 0.39313512375368537,
    "header_carrier_phase_only_peak": 1.0,
    "header_carrier_phase_only_score": 0.8927257984243537,
    "header_carrier_phase_only_error": 0.3931368334631258,
    "header_carrier_phase_slope_peak": 1.0,
    "header_carrier_phase_slope_score": 0.892725703686306,
    "header_carrier_phase_slope_error": 0.39313512375368537,
    "short_equalizer_enabled": true,
    "short_equalizer_applied": true,
    "short_equalizer_reason": "header_error_improved_peak_within_tol",
    "short_equalizer_tap_count": 5,
    "short_equalizer_training_symbols": 434,
    "short_equalizer_valid_training_symbols": 434,
    "short_equalizer_before_error": 0.5744989015855101,
    "short_equalizer_after_error": 0.4539494578760793,
    "short_equalizer_before_mse": 0.3515356261879514,
    "short_equalizer_after_mse": 0.22036750399626595,
    "short_equalizer_mse_relative_improvement": 0.37312895883148794,
    "short_equalizer_mse_relative_improvement_min": 0.05,
    "short_equalizer_peak_tolerance": 0.001,
    "short_equalizer_baseline_header_peak": 1.0,
    "short_equalizer_baseline_header_error": 0.39313512375368537,
    "short_equalizer_post_header_peak": 1.0,
    "short_equalizer_post_header_error": 0.2373639971896722,
    "short_equalizer_post_header_score": 0.9671383453070461,
    "short_equalizer_header_peak_improved": false,
    "short_equalizer_header_peak_within_tol": true,
    "short_equalizer_header_error_improved": true,
    "short_equalizer_header_error_not_worse": true,
    "short_equalizer_accepted_via_header_error": true,
    "short_equalizer_accepted_via_training_mse": true,
    "short_equalizer_header_gate_passed": true,
    "short_equalizer_acceptance_reason": "header_error_improved_peak_within_tol",
    "short_equalizer_rejection_reason": "",
    "short_equalizer_post_header_best_index": 372,
    "midamble_alignment_enabled": true,
    "midamble_alignment_applied": false,
    "midamble_alignment_reason": "not_improved",
    "midamble_expected_index": 1458,
    "midamble_best_index": 1458,
    "midamble_slip_symbols": 0,
    "midamble_score": 0.9806037273411455,
    "midamble_peak": 1.0,
    "midamble_phase_rad": 0.0,
    "midamble_error": 0.12224450079267597,
    "costas_update_start_symbol": 372,
    "costas_update_stop_symbol": 12808,
    "costas_gate_reference_power": 0.42487502098083496,
    "costas_gate_min_power": 0.195673868060112,
    "costas_gate_max_power": 0.6946915984153748,
    "costas_update_rate": 0.6773014068603516,
    "timing_nearest_symbol_error": 0.4788125157356262,
    "carrier_aligned_nearest_symbol_error": 0.48335617780685425,
    "equalized_nearest_symbol_error": 0.3886447548866272,
    "fine_nearest_symbol_error": 0.372785359621048,
    "tx_symbols": 12872,
    "payload_symbols": 12312,
    "gold_header_symbols": 62,
    "guard_symbols": 32,
    "detected": true,
    "detected_index": 372,
    "decode_candidate_count": 1,
    "decode_candidate_min_peak": 0.65,
    "decode_candidates_ranked": 5,
    "decode_candidates_attempted": 1,
    "expected_header_index": 372,
    "timing_window_expected_header_index": 372,
    "header_detect_ok": true,
    "peak": 1.0,
    "best_symbol_phase": 0,
    "detection_rotation": "(1+0j)",
    "recovered_ok": true,
    "decode_rotation": "(1+0j)",
    "decode_error": "",
    "recovered_text": "hardware test ",
    "costas_error_mean": -0.1906532198190689,
    "costas_error_variance": 0.015633895993232727,
    "costas_phase_span": 0.01809244230389595,
    "gardner_error_mean": 0.002838742919266224,
    "gardner_error_variance": 0.013809979893267155,
    "run_index": 2
  },
  {
    "payload_length_bytes": 14,
    "rx_samples": 262144,
    "sync_preamble_symbols": 372,
    "channel_payload_symbols": 12374,
    "midamble_symbols": 62,
    "midamble_applied": true,
    "sync_input_samples": 262144,
    "sync_input_offset": 0,
    "burst_crop_window_samples": 102976,
    "burst_crop_margin_samples": 80,
    "burst_crop_full_buffer_fallback": false,
    "header_alignment_detected": true,
    "header_alignment_applied": true,
    "header_alignment_soft_selected": false,
    "header_alignment_peak": 0.9987137317657471,
    "header_alignment_phase_score": 0.9999386072158813,
    "header_alignment_peak_ratio": 1.0415915237622735,
    "header_alignment_start_sample": 142349,
    "header_alignment_offset_samples": 142333,
    "header_phase": 4,
    "header_phase_score": 0.9999386072158813,
    "header_phase_offset_samples": -4,
    "refined_header_start_sample": 12,
    "matched_rms_before": 399.4420471191406,
    "matched_normalization_scale": 0.0025034920765407863,
    "matched_normalization_selected_samples": 91751,
    "fractional_timing_enabled": true,
    "fractional_timing_applied": true,
    "fractional_timing_reason": "applied",
    "fractional_timing_sample_offset": -1.0,
    "fractional_timing_baseline_header_peak": 0.6129032373428345,
    "fractional_timing_baseline_header_error": 0.5447712719422877,
    "fractional_timing_header_peak": 1.0,
    "fractional_timing_header_error": 0.3930780221597029,
    "fractional_timing_best_index": 374,
    "timing_header_index": 372,
    "timing_header_peak": 1.0,
    "timing_header_rotation": "(1+0j)",
    "timing_header_detect_ok": true,
    "timing_header_best_index": 372,
    "timing_header_best_index_error": 0,
    "timing_header_slip_symbols": 0,
    "timing_header_slip_applied": false,
    "timing_header_error": 0.3930780221597029,
    "timing_header_index_error": 0,
    "header_phase_symbol_index": 372,
    "timing_window_start_sample": 4,
    "timing_window_stop_sample": 102820,
    "timing_window_samples": 102816,
    "timing_window_requested_symbols": 12850,
    "timing_window_available_symbols": 12852,
    "timing_window_expected_preamble_index": 0,
    "timing_window_active_symbols": 12808,
    "timing_window_tracking_payload_symbols": 64,
    "timing_window_tracking_symbols": 498,
    "timing_window_post_symbols": 412,
    "gardner_update_start_sample": 0,
    "gardner_update_stop_sample": 3984,
    "gardner_gate_min_energy": 1.0959025919437408,
    "gardner_gate_max_energy": 4.811821460723877,
    "gardner_update_rate": 0.03867403417825699,
    "gardner_mu_final": 0.026483535766601562,
    "gardner_omega_final": 8.000001907348633,
    "preamble_cfo_enabled": true,
    "preamble_cfo_repeat_count": 12,
    "preamble_cfo_repeat_length_symbols": 31,
    "preamble_cfo_symbol_index": 0,
    "preamble_cfo_score": 0.988943678489575,
    "preamble_cfo_reason": "applied",
    "preamble_cfo_phase_slope_rad_per_symbol": 5.482693417041084e-06,
    "preamble_cfo_applied_slope_rad_per_symbol": 5.482693417041084e-06,
    "preamble_cfo_frequency_hz": 0.10907471984743536,
    "preamble_cfo_applied_frequency_hz": 0.10907471984743536,
    "preamble_symbol_best_index": 2,
    "preamble_symbol_score": 0.9070924017234738,
    "preamble_symbol_peak_ratio": 1.0117636411218909,
    "preamble_symbol_slip_symbols": 2,
    "preamble_symbol_alignment_applied": true,
    "preamble_symbol_alignment_reason": "applied",
    "header_carrier_phase_rad": -1.0880239102360927,
    "header_carrier_phase_slope_rad_per_symbol": -1.679355398169903e-05,
    "header_carrier_frequency_hz": -0.33409714103349764,
    "header_carrier_score": 0.8931026612885401,
    "header_carrier_applied_slope_rad_per_symbol": -1.679355398169903e-05,
    "header_carrier_applied_frequency_hz": -0.33409714103349764,
    "header_carrier_slope_applied": true,
    "header_carrier_slope_reason": "applied",
    "header_carrier_branch_selection_enabled": true,
    "header_carrier_selected_branch": "phase_slope",
    "header_carrier_selection_reason": "best_header_error",
    "header_carrier_selected_detect_peak": 1.0,
    "header_carrier_selected_header_score": 0.8931026104401468,
    "header_carrier_selected_header_error": 0.3930767475133231,
    "header_carrier_phase_only_peak": 1.0,
    "header_carrier_phase_only_score": 0.8931025465137116,
    "header_carrier_phase_only_error": 0.39307802373360484,
    "header_carrier_phase_slope_peak": 1.0,
    "header_carrier_phase_slope_score": 0.8931026104401468,
    "header_carrier_phase_slope_error": 0.3930767475133231,
    "short_equalizer_enabled": true,
    "short_equalizer_applied": true,
    "short_equalizer_reason": "header_error_improved_peak_within_tol",
    "short_equalizer_tap_count": 5,
    "short_equalizer_training_symbols": 434,
    "short_equalizer_valid_training_symbols": 434,
    "short_equalizer_before_error": 0.5734629006795341,
    "short_equalizer_after_error": 0.449957603413373,
    "short_equalizer_before_mse": 0.34957387889134095,
    "short_equalizer_after_mse": 0.21697597390692325,
    "short_equalizer_mse_relative_improvement": 0.3793129664177039,
    "short_equalizer_mse_relative_improvement_min": 0.05,
    "short_equalizer_peak_tolerance": 0.001,
    "short_equalizer_baseline_header_peak": 1.0,
    "short_equalizer_baseline_header_error": 0.3930767475133231,
    "short_equalizer_post_header_peak": 1.0,
    "short_equalizer_post_header_error": 0.2369499375882479,
    "short_equalizer_post_header_score": 0.9672574691467913,
    "short_equalizer_header_peak_improved": false,
    "short_equalizer_header_peak_within_tol": true,
    "short_equalizer_header_error_improved": true,
    "short_equalizer_header_error_not_worse": true,
    "short_equalizer_accepted_via_header_error": true,
    "short_equalizer_accepted_via_training_mse": true,
    "short_equalizer_header_gate_passed": true,
    "short_equalizer_acceptance_reason": "header_error_improved_peak_within_tol",
    "short_equalizer_rejection_reason": "",
    "short_equalizer_post_header_best_index": 372,
    "midamble_alignment_enabled": true,
    "midamble_alignment_applied": false,
    "midamble_alignment_reason": "not_improved",
    "midamble_expected_index": 1458,
    "midamble_best_index": 1458,
    "midamble_slip_symbols": 0,
    "midamble_score": 0.980154115515246,
    "midamble_peak": 1.0,
    "midamble_phase_rad": 0.0,
    "midamble_error": 0.12363117327148827,
    "costas_update_start_symbol": 372,
    "costas_update_stop_symbol": 12808,
    "costas_gate_reference_power": 0.413002073764801,
    "costas_gate_min_power": 0.19658541679382324,
    "costas_gate_max_power": 0.6953859329223633,
    "costas_update_rate": 0.6773014068603516,
    "timing_nearest_symbol_error": 1.0754998922348022,
    "carrier_aligned_nearest_symbol_error": 0.45703357458114624,
    "equalized_nearest_symbol_error": 0.36991357803344727,
    "fine_nearest_symbol_error": 0.3678441345691681,
    "tx_symbols": 12872,
    "payload_symbols": 12312,
    "gold_header_symbols": 62,
    "guard_symbols": 32,
    "detected": true,
    "detected_index": 372,
    "decode_candidate_count": 1,
    "decode_candidate_min_peak": 0.65,
    "decode_candidates_ranked": 5,
    "decode_candidates_attempted": 1,
    "expected_header_index": 372,
    "timing_window_expected_header_index": 372,
    "header_detect_ok": true,
    "peak": 1.0,
    "best_symbol_phase": 0,
    "detection_rotation": "(1+0j)",
    "recovered_ok": true,
    "decode_rotation": "(1+0j)",
    "decode_error": "",
    "recovered_text": "hardware test ",
    "costas_error_mean": 0.052771516144275665,
    "costas_error_variance": 0.003068431979045272,
    "costas_phase_span": 0.005694675259292126,
    "gardner_error_mean": 0.00137517717666924,
    "gardner_error_variance": 0.013773667626082897,
    "run_index": 3
  },
  {
    "payload_length_bytes": 14,
    "rx_samples": 262144,
    "sync_preamble_symbols": 372,
    "channel_payload_symbols": 12374,
    "midamble_symbols": 62,
    "midamble_applied": true,
    "sync_input_samples": 262144,
    "sync_input_offset": 0,
    "burst_crop_window_samples": 102976,
    "burst_crop_margin_samples": 80,
    "burst_crop_full_buffer_fallback": false,
    "header_alignment_detected": true,
    "header_alignment_applied": true,
    "header_alignment_soft_selected": false,
    "header_alignment_peak": 0.7973783016204834,
    "header_alignment_phase_score": 0.7958199381828308,
    "header_alignment_peak_ratio": 1.0065132475809782,
    "header_alignment_start_sample": 137365,
    "header_alignment_offset_samples": 137349,
    "header_phase": 4,
    "header_phase_score": 0.7958199381828308,
    "header_phase_offset_samples": -4,
    "refined_header_start_sample": 12,
    "matched_rms_before": 384.31732177734375,
    "matched_normalization_scale": 0.002602016467473603,
    "matched_normalization_selected_samples": 91751,
    "fractional_timing_enabled": true,
    "fractional_timing_applied": true,
    "fractional_timing_reason": "applied",
    "fractional_timing_sample_offset": -1.0,
    "fractional_timing_baseline_header_peak": 0.5806451439857483,
    "fractional_timing_baseline_header_error": 0.5450696062023783,
    "fractional_timing_header_peak": 1.0,
    "fractional_timing_header_error": 0.39323473793098146,
    "fractional_timing_best_index": 374,
    "timing_header_index": 372,
    "timing_header_peak": 1.0,
    "timing_header_rotation": "(1+0j)",
    "timing_header_detect_ok": true,
    "timing_header_best_index": 372,
    "timing_header_best_index_error": 0,
    "timing_header_slip_symbols": 0,
    "timing_header_slip_applied": false,
    "timing_header_error": 0.39323473793098146,
    "timing_header_index_error": 0,
    "header_phase_symbol_index": 372,
    "timing_window_start_sample": 4,
    "timing_window_stop_sample": 102820,
    "timing_window_samples": 102816,
    "timing_window_requested_symbols": 12850,
    "timing_window_available_symbols": 12852,
    "timing_window_expected_preamble_index": 0,
    "timing_window_active_symbols": 12808,
    "timing_window_tracking_payload_symbols": 64,
    "timing_window_tracking_symbols": 498,
    "timing_window_post_symbols": 412,
    "gardner_update_start_sample": 0,
    "gardner_update_stop_sample": 3984,
    "gardner_gate_min_energy": 1.0966310799121857,
    "gardner_gate_max_energy": 4.792630434036255,
    "gardner_update_rate": 0.03867403417825699,
    "gardner_mu_final": 0.05015754699707031,
    "gardner_omega_final": 8.000003814697266,
    "preamble_cfo_enabled": true,
    "preamble_cfo_repeat_count": 12,
    "preamble_cfo_repeat_length_symbols": 31,
    "preamble_cfo_symbol_index": 0,
    "preamble_cfo_score": 0.9889998221481903,
    "preamble_cfo_reason": "applied",
    "preamble_cfo_phase_slope_rad_per_symbol": 0.006127802932782553,
    "preamble_cfo_applied_slope_rad_per_symbol": 0.006127802932782553,
    "preamble_cfo_frequency_hz": 121.90876588066958,
    "preamble_cfo_applied_frequency_hz": 121.90876588066958,
    "preamble_symbol_best_index": 2,
    "preamble_symbol_score": 0.9078517844609679,
    "preamble_symbol_peak_ratio": 1.0117428825740102,
    "preamble_symbol_slip_symbols": 2,
    "preamble_symbol_alignment_applied": true,
    "preamble_symbol_alignment_reason": "applied",
    "header_carrier_phase_rad": -2.604777628197822,
    "header_carrier_phase_slope_rad_per_symbol": 3.979603881753252e-05,
    "header_carrier_frequency_hz": 0.7917170366609058,
    "header_carrier_score": 0.8926741274573086,
    "header_carrier_applied_slope_rad_per_symbol": 3.979603881753252e-05,
    "header_carrier_applied_frequency_hz": 0.7917170366609058,
    "header_carrier_slope_applied": true,
    "header_carrier_slope_reason": "applied",
    "header_carrier_branch_selection_enabled": true,
    "header_carrier_selected_branch": "phase_slope",
    "header_carrier_selection_reason": "best_header_error",
    "header_carrier_selected_detect_peak": 1.0,
    "header_carrier_selected_header_score": 0.8926740694857647,
    "header_carrier_selected_header_error": 0.3932334400596425,
    "header_carrier_phase_only_peak": 1.0,
    "header_carrier_phase_only_score": 0.8926740397178086,
    "header_carrier_phase_only_error": 0.39323473860708574,
    "header_carrier_phase_slope_peak": 1.0,
    "header_carrier_phase_slope_score": 0.8926740694857647,
    "header_carrier_phase_slope_error": 0.3932334400596425,
    "short_equalizer_enabled": true,
    "short_equalizer_applied": true,
    "short_equalizer_reason": "header_error_improved_peak_within_tol",
    "short_equalizer_tap_count": 5,
    "short_equalizer_training_symbols": 434,
    "short_equalizer_valid_training_symbols": 434,
    "short_equalizer_before_error": 0.5704547359556145,
    "short_equalizer_after_error": 0.447591978330629,
    "short_equalizer_before_mse": 0.34613639347346026,
    "short_equalizer_after_mse": 0.21472201714189765,
    "short_equalizer_mse_relative_improvement": 0.3796606736807602,
    "short_equalizer_mse_relative_improvement_min": 0.05,
    "short_equalizer_peak_tolerance": 0.001,
    "short_equalizer_baseline_header_peak": 1.0,
    "short_equalizer_baseline_header_error": 0.3932334400596425,
    "short_equalizer_post_header_peak": 1.0,
    "short_equalizer_post_header_error": 0.23778263558838877,
    "short_equalizer_post_header_score": 0.9672861937907387,
    "short_equalizer_header_peak_improved": false,
    "short_equalizer_header_peak_within_tol": true,
    "short_equalizer_header_error_improved": true,
    "short_equalizer_header_error_not_worse": true,
    "short_equalizer_accepted_via_header_error": true,
    "short_equalizer_accepted_via_training_mse": true,
    "short_equalizer_header_gate_passed": true,
    "short_equalizer_acceptance_reason": "header_error_improved_peak_within_tol",
    "short_equalizer_rejection_reason": "",
    "short_equalizer_post_header_best_index": 372,
    "midamble_alignment_enabled": true,
    "midamble_alignment_applied": false,
    "midamble_alignment_reason": "not_improved",
    "midamble_expected_index": 1458,
    "midamble_best_index": 1458,
    "midamble_slip_symbols": 0,
    "midamble_score": 0.9799459650101817,
    "midamble_peak": 1.0,
    "midamble_phase_rad": 0.0,
    "midamble_error": 0.12467502343823406,
    "costas_update_start_symbol": 372,
    "costas_update_stop_symbol": 12808,
    "costas_gate_reference_power": 0.41411811113357544,
    "costas_gate_min_power": 0.19798415899276733,
    "costas_gate_max_power": 0.6912773847579956,
    "costas_update_rate": 0.6773014068603516,
    "timing_nearest_symbol_error": 0.6773747801780701,
    "carrier_aligned_nearest_symbol_error": 0.549972414970398,
    "equalized_nearest_symbol_error": 0.4471713900566101,
    "fine_nearest_symbol_error": 0.3920612633228302,
    "tx_symbols": 12872,
    "payload_symbols": 12312,
    "gold_header_symbols": 62,
    "guard_symbols": 32,
    "detected": true,
    "detected_index": 372,
    "decode_candidate_count": 1,
    "decode_candidate_min_peak": 0.65,
    "decode_candidates_ranked": 5,
    "decode_candidates_attempted": 1,
    "expected_header_index": 372,
    "timing_window_expected_header_index": 372,
    "header_detect_ok": true,
    "peak": 1.0,
    "best_symbol_phase": 0,
    "detection_rotation": "(1+0j)",
    "recovered_ok": true,
    "decode_rotation": "(1+0j)",
    "decode_error": "",
    "recovered_text": "hardware test ",
    "costas_error_mean": -0.3476194739341736,
    "costas_error_variance": 0.026876650750637054,
    "costas_phase_span": 0.03399532288312912,
    "gardner_error_mean": 0.002842941554263234,
    "gardner_error_variance": 0.013797152787446976,
    "run_index": 4
  },
  {
    "payload_length_bytes": 14,
    "rx_samples": 262144,
    "sync_preamble_symbols": 372,
    "channel_payload_symbols": 12374,
    "midamble_symbols": 62,
    "midamble_applied": true,
    "sync_input_samples": 262144,
    "sync_input_offset": 0,
    "burst_crop_window_samples": 102976,
    "burst_crop_margin_samples": 80,
    "burst_crop_full_buffer_fallback": false,
    "header_alignment_detected": true,
    "header_alignment_applied": true,
    "header_alignment_soft_selected": false,
    "header_alignment_peak": 0.9987258315086365,
    "header_alignment_phase_score": 0.9999589323997498,
    "header_alignment_peak_ratio": 1.041613531806257,
    "header_alignment_start_sample": 140607,
    "header_alignment_offset_samples": 140591,
    "header_phase": 4,
    "header_phase_score": 0.9999589323997498,
    "header_phase_offset_samples": -4,
    "refined_header_start_sample": 12,
    "matched_rms_before": 396.9449768066406,
    "matched_normalization_scale": 0.0025192408480511365,
    "matched_normalization_selected_samples": 91751,
    "fractional_timing_enabled": true,
    "fractional_timing_applied": true,
    "fractional_timing_reason": "applied",
    "fractional_timing_sample_offset": -1.0,
    "fractional_timing_baseline_header_peak": 0.6129032373428345,
    "fractional_timing_baseline_header_error": 0.5448386453284803,
    "fractional_timing_header_peak": 1.0,
    "fractional_timing_header_error": 0.39322523630466993,
    "fractional_timing_best_index": 374,
    "timing_header_index": 372,
    "timing_header_peak": 1.0,
    "timing_header_rotation": "(1+0j)",
    "timing_header_detect_ok": true,
    "timing_header_best_index": 372,
    "timing_header_best_index_error": 0,
    "timing_header_slip_symbols": 0,
    "timing_header_slip_applied": false,
    "timing_header_error": 0.39322523630466993,
    "timing_header_index_error": 0,
    "header_phase_symbol_index": 372,
    "timing_window_start_sample": 4,
    "timing_window_stop_sample": 102820,
    "timing_window_samples": 102816,
    "timing_window_requested_symbols": 12850,
    "timing_window_available_symbols": 12852,
    "timing_window_expected_preamble_index": 0,
    "timing_window_active_symbols": 12808,
    "timing_window_tracking_payload_symbols": 64,
    "timing_window_tracking_symbols": 498,
    "timing_window_post_symbols": 412,
    "gardner_update_start_sample": 0,
    "gardner_update_stop_sample": 3984,
    "gardner_gate_min_energy": 1.114097535610199,
    "gardner_gate_max_energy": 4.87935197353363,
    "gardner_update_rate": 0.03867403417825699,
    "gardner_mu_final": 0.0501556396484375,
    "gardner_omega_final": 8.000003814697266,
    "preamble_cfo_enabled": true,
    "preamble_cfo_repeat_count": 12,
    "preamble_cfo_repeat_length_symbols": 31,
    "preamble_cfo_symbol_index": 0,
    "preamble_cfo_score": 0.9884873347568772,
    "preamble_cfo_reason": "applied",
    "preamble_cfo_phase_slope_rad_per_symbol": 4.796495731498842e-06,
    "preamble_cfo_applied_slope_rad_per_symbol": 4.796495731498842e-06,
    "preamble_cfo_frequency_hz": 0.09542325064840214,
    "preamble_cfo_applied_frequency_hz": 0.09542325064840214,
    "preamble_symbol_best_index": 2,
    "preamble_symbol_score": 0.9077531822424398,
    "preamble_symbol_peak_ratio": 1.011798587935252,
    "preamble_symbol_slip_symbols": 2,
    "preamble_symbol_alignment_applied": true,
    "preamble_symbol_alignment_reason": "applied",
    "header_carrier_phase_rad": -1.2527519768082875,
    "header_carrier_phase_slope_rad_per_symbol": -1.0106062917869797e-05,
    "header_carrier_frequency_hz": -0.20105373357208514,
    "header_carrier_score": 0.8927028039686162,
    "header_carrier_applied_slope_rad_per_symbol": -1.0106062917869797e-05,
    "header_carrier_applied_frequency_hz": -0.20105373357208514,
    "header_carrier_slope_applied": true,
    "header_carrier_slope_reason": "applied",
    "header_carrier_branch_selection_enabled": true,
    "header_carrier_selected_branch": "phase_slope",
    "header_carrier_selection_reason": "best_header_error",
    "header_carrier_selected_detect_peak": 1.0,
    "header_carrier_selected_header_score": 0.8927029319838468,
    "header_carrier_selected_header_error": 0.39322328732245654,
    "header_carrier_phase_only_peak": 1.0,
    "header_carrier_phase_only_score": 0.8927028639358415,
    "header_carrier_phase_only_error": 0.39322523871127524,
    "header_carrier_phase_slope_peak": 1.0,
    "header_carrier_phase_slope_score": 0.8927029319838468,
    "header_carrier_phase_slope_error": 0.39322328732245654,
    "short_equalizer_enabled": true,
    "short_equalizer_applied": true,
    "short_equalizer_reason": "header_error_improved_peak_within_tol",
    "short_equalizer_tap_count": 5,
    "short_equalizer_training_symbols": 434,
    "short_equalizer_valid_training_symbols": 434,
    "short_equalizer_before_error": 0.5868131739826363,
    "short_equalizer_after_error": 0.4829150324822872,
    "short_equalizer_before_mse": 0.3702015099551466,
    "short_equalizer_after_mse": 0.2459532026701523,
    "short_equalizer_mse_relative_improvement": 0.33562344815948525,
    "short_equalizer_mse_relative_improvement_min": 0.05,
    "short_equalizer_peak_tolerance": 0.001,
    "short_equalizer_baseline_header_peak": 1.0,
    "short_equalizer_baseline_header_error": 0.39322328732245654,
    "short_equalizer_post_header_peak": 1.0,
    "short_equalizer_post_header_error": 0.23874314412352443,
    "short_equalizer_post_header_score": 0.9668104494573942,
    "short_equalizer_header_peak_improved": false,
    "short_equalizer_header_peak_within_tol": true,
    "short_equalizer_header_error_improved": true,
    "short_equalizer_header_error_not_worse": true,
    "short_equalizer_accepted_via_header_error": true,
    "short_equalizer_accepted_via_training_mse": true,
    "short_equalizer_header_gate_passed": true,
    "short_equalizer_acceptance_reason": "header_error_improved_peak_within_tol",
    "short_equalizer_rejection_reason": "",
    "short_equalizer_post_header_best_index": 372,
    "midamble_alignment_enabled": true,
    "midamble_alignment_applied": false,
    "midamble_alignment_reason": "not_improved",
    "midamble_expected_index": 1458,
    "midamble_best_index": 1458,
    "midamble_slip_symbols": 0,
    "midamble_score": 0.9800723876369071,
    "midamble_peak": 1.0,
    "midamble_phase_rad": 0.0,
    "midamble_error": 0.12412054774525286,
    "costas_update_start_symbol": 372,
    "costas_update_stop_symbol": 12808,
    "costas_gate_reference_power": 0.3950287103652954,
    "costas_gate_min_power": 0.19546470046043396,
    "costas_gate_max_power": 0.6963747143745422,
    "costas_update_rate": 0.6773014068603516,
    "timing_nearest_symbol_error": 1.0860024690628052,
    "carrier_aligned_nearest_symbol_error": 0.4941067397594452,
    "equalized_nearest_symbol_error": 0.4007273316383362,
    "fine_nearest_symbol_error": 0.37562358379364014,
    "tx_symbols": 12872,
    "payload_symbols": 12312,
    "gold_header_symbols": 62,
    "guard_symbols": 32,
    "detected": true,
    "detected_index": 372,
    "decode_candidate_count": 1,
    "decode_candidate_min_peak": 0.65,
    "decode_candidates_ranked": 5,
    "decode_candidates_attempted": 1,
    "expected_header_index": 372,
    "timing_window_expected_header_index": 372,
    "header_detect_ok": true,
    "peak": 1.0,
    "best_symbol_phase": 0,
    "detection_rotation": "(1+0j)",
    "recovered_ok": true,
    "decode_rotation": "(1+0j)",
    "decode_error": "",
    "recovered_text": "hardware test ",
    "costas_error_mean": 0.2134004682302475,
    "costas_error_variance": 0.025411229580640793,
    "costas_phase_span": 0.02105320617556572,
    "gardner_error_mean": 0.0028540976345539093,
    "gardner_error_variance": 0.013796208426356316,
    "run_index": 5
  }
]